{"format":"doc","file_size":34.0,"size_format":"Мб","title":"Собор Парижской Богоматери","pages":222,"publishers":"ЛитРес","upload":"2020-03-29T17:18:55","author":{"id":0,"name":"В.Гюго","country":"Франция"}}
{"format":"docx","file_size":240.0,"size_format":"Мб","title":"Отверженные","pages":617,"publishers":"Питер","upload":"2020-03-29T17:20:55","author":{"id":3,"name":"В.Гюго","country":"Франция"}}
{"format":"doc","file_size":1.2,"size_format":"Гб","title":"Война и Мир","pages":946,"publishers":"Вестник","upload":"2020-03-29T17:22:26","author":{"id":5,"name":"Л.Толстой","country":"Россия"}}
{"format":"docx","file_size":400.0,"size_format":"Мб","title":"Побег из Шоушенка","pages":569,"publishers":"ЛитРес","upload":"2020-03-29T17:22:26","author":{"id":7,"name":"С.Кинг","country":"США"}}
{"format":"pdf","file_size":420.0,"size_format":"Мб","title":"Сияние","pages":474,"publishers":"Питер","upload":"2020-03-29T17:22:26","author":{"id":9,"name":"С.Кинг","country":"США"}}
{"format":"txt","file_size":120.0,"size_format":"Мб","title":"Над пропастью во ржи","pages":246,"publishers":"Питер","upload":"2020-03-29T17:22:26","author":{"id":11,"name":"Д.Сэлинджер","country":"США"}}
{"format":"doc","file_size":0.9,"size_format":"Гб","title":"Жестяной барабан","pages":707,"publishers":"Вестник","upload":"2020-03-29T17:22:26","author":{"id":13,"name":"Г.Грасс","country":"Германия"}}
{"format":"pdf","file_size":368.0,"size_format":"Мб","title":"Фауст","pages":228,"publishers":"Питер","upload":"2020-03-29T17:22:26","author":{"id":15,"name":"И.Гете","country":"Германия"}}
{"format":"txt","file_size":450.0,"size_format":"Мб","title":"Белая гвардия","pages":342,"publishers":"Вестник","upload":"2020-03-29T17:22:26","author":{"id":17,"name":"М.Булгаков","country":"Россия"}}
{"format":"docx","file_size":1.2,"size_format":"Гб","title":"Три мушкетера","pages":557,"publishers":"ЛитРес","upload":"2020-03-29T17:22:26","author":{"id":19,"name":"А.Дюма","country":"Франция"}}
{"format":"pdf","file_size":678.0,"size_format":"Мб","title":"Три товарища","pages":354,"publishers":"Минск","upload":"2020-03-29T22:18:46","author":{"id":10,"name":"Э.Ремарк","country":"Германия"}}
{"upload":"2020-04-03T23:45:57","author":{"id":4,"name":"В.Набоков","country":"США"},"format":"docx","file_size":34.0,"size_format":"Мб","title":"Лолита","pages":66,"publishers":"Питер"}
